{
  "tests" : [ {
    "name" : "Home page on Safari on Mac browser",
    "startedAt" : 1439919863420,
    "endedAt" : 1439919889394,
    "failed" : true,
    "statistic" : {
      "passed" : 2,
      "errors" : 2,
      "warnings" : 0,
      "total" : 4
    },
    "testId" : "1-home-page-on-safari-on-mac-browser",
    "failed" : true,
    "duration" : 25974
  }, {
    "name" : "Home page on Opera browser",
    "startedAt" : 1439919889394,
    "endedAt" : 1439919901151,
    "failed" : true,
    "statistic" : {
      "passed" : 2,
      "errors" : 2,
      "warnings" : 0,
      "total" : 4
    },
    "testId" : "2-home-page-on-opera-browser",
    "failed" : true,
    "duration" : 11757
  }, {
    "name" : "Home page on Firefox browser",
    "startedAt" : 1439919901151,
    "endedAt" : 1439919913906,
    "failed" : true,
    "statistic" : {
      "passed" : 2,
      "errors" : 2,
      "warnings" : 0,
      "total" : 4
    },
    "testId" : "3-home-page-on-firefox-browser",
    "failed" : true,
    "duration" : 12755
  }, {
    "name" : "Home page on Chrome browser",
    "startedAt" : 1439919913906,
    "endedAt" : 1439919922073,
    "failed" : true,
    "statistic" : {
      "passed" : 2,
      "errors" : 2,
      "warnings" : 0,
      "total" : 4
    },
    "testId" : "4-home-page-on-chrome-browser",
    "failed" : true,
    "duration" : 8167
  }, {
    "name" : "Home page on IE 11 browser",
    "startedAt" : 1439919922074,
    "endedAt" : 1439919938269,
    "failed" : true,
    "statistic" : {
      "passed" : 2,
      "errors" : 2,
      "warnings" : 0,
      "total" : 4
    },
    "testId" : "5-home-page-on-ie-11-browser",
    "failed" : true,
    "duration" : 16195
  } ]
}